patch_antenna/__init__.py
patch_antenna/comparison.py
patch_antenna/designer.py
patch_antenna/export.py
patch_antenna/frequency_bands.py
patch_antenna/materials.py
patch_antenna/validation.py
patch_antenna_designer-1.0.0.dist-info/licenses/LICENSE
patch_antenna_designer-1.0.0.dist-info/METADATA
patch_antenna_designer-1.0.0.dist-info/WHEEL
patch_antenna_designer-1.0.0.dist-info/top_level.txt
patch_antenna_designer-1.0.0.dist-info/RECORD
