Metadata-Version: 2.4
Name: patch-antenna-designer
Version: 1.0.0
Summary: Advanced patch antenna design with material database and automated Gerber generation
Home-page: https://github.com/space-comms/patch_antenna
Author: Al-Musbahi
Author-email: Al-Musbahi <musbahi.git@gmail.com>, Bhanuchander Udhayakumar <bhanuchander210@gmail.com>
Maintainer: Leeds SpaceComms
License: MIT
Project-URL: Homepage, https://github.com/space-comms/patch_antenna
Project-URL: Documentation, https://github.com/space-comms/patch_antenna#readme
Project-URL: Repository, https://github.com/space-comms/patch_antenna
Project-URL: Bug Reports, https://github.com/space-comms/patch_antenna/issues
Keywords: antenna,design,patch,microstrip,rf,gerber,pcb
Classifier: Development Status :: 5 - Production/Stable
Classifier: Intended Audience :: Science/Research
Classifier: Intended Audience :: Developers
Classifier: License :: OSI Approved :: MIT License
Classifier: Programming Language :: Python :: 3
Classifier: Programming Language :: Python :: 3.7
Classifier: Programming Language :: Python :: 3.8
Classifier: Programming Language :: Python :: 3.9
Classifier: Programming Language :: Python :: 3.10
Classifier: Programming Language :: Python :: 3.11
Classifier: Programming Language :: Python :: 3.12
Classifier: Topic :: Scientific/Engineering
Classifier: Topic :: Software Development :: Libraries :: Python Modules
Requires-Python: >=3.7
License-File: LICENSE
Requires-Dist: scipy>=1.9.0
Requires-Dist: gerber-writer>=0.3.4
Provides-Extra: dev
Requires-Dist: pytest; extra == "dev"
Requires-Dist: pytest-cov; extra == "dev"
Requires-Dist: flake8; extra == "dev"
Provides-Extra: docs
Requires-Dist: sphinx; extra == "docs"
Requires-Dist: sphinx-rtd-theme; extra == "docs"
Dynamic: author
Dynamic: home-page
Dynamic: license-file
Dynamic: requires-python
